glossary/__init__.py
glossary/glossary.py
glossary/tests.py
pmx_glossary/__init__.py
pmx_glossary/cli.py
pmx_glossary/glossary.py
pmx_glossary/tests.py
pmxbot_glossary-0.4.2.dist-info/DESCRIPTION.rst
pmxbot_glossary-0.4.2.dist-info/entry_points.txt
pmxbot_glossary-0.4.2.dist-info/METADATA
pmxbot_glossary-0.4.2.dist-info/metadata.json
pmxbot_glossary-0.4.2.dist-info/RECORD
pmxbot_glossary-0.4.2.dist-info/top_level.txt
pmxbot_glossary-0.4.2.dist-info/WHEEL
