Metadata-Version: 2.0
Name: pmxbot-glossary
Version: 0.4.2
Summary: A pmxbot glossary extension.
Home-page: https://github.com/harveyr/pmxbot-glossary/
Author: Harvey Rogers
Author-email: harveyr@gmail.com 
License: MIT
Platform: UNKNOWN
Requires-Dist: pmxbot
Requires-Dist: python-dateutil
Requires-Dist: click
